pdftabextract/__init__.py
pdftabextract/clustering.py
pdftabextract/common.py
pdftabextract/extract.py
pdftabextract/geom.py
pdftabextract/imgproc.py
pdftabextract/splitpages.py
pdftabextract/textboxes.py
pdftabextract-0.3.0.dist-info/DESCRIPTION.rst
pdftabextract-0.3.0.dist-info/METADATA
pdftabextract-0.3.0.dist-info/RECORD
pdftabextract-0.3.0.dist-info/WHEEL
pdftabextract-0.3.0.dist-info/metadata.json
pdftabextract-0.3.0.dist-info/top_level.txt
